{
  "eatmenuCollection": [
    {
      "name": "ROZVOZ COKOLIF",
      "description": "ROZVOZ   :::::   POND캨L칈 - P츼TEK  11.01 - 16.01 hod.  ::::::  游댵TEL. 728 758 632 "
    },
    {
      "name": "Menu",
      "description": "MENU 11. 5. - 15. 5. 2020  :::::::   POZOR : Na코e MENU se m콢쬰 v pr콢b캩hu t칳dne M캨NIT a mohou t콏eba p콏ib칳vat i n캩kter칠 pokrmy, tak bu캞te ve st콏ehu! :)",
      "price": ""
    },
    {
      "name": "POND캨L칈 - Pol칠vka",
      "description": "POND캨L칈 - POL칄VKA :::: Kuku콏i캜n칳 kr칠m s chilli vlasy a 캜erstv칳m koriandrem  A: 1,7",
      "price": 47
    },
    {
      "name": "POND캨L칈 - Hlavn칤 chod",
      "description": "POND캨L칈 - HLAVN칈 CHOD :::  Burger s trhan칳m vep콏ov칳m bokem, 캜erstv칳m koriandrem, sriracha majon칠zou a dom치c칤m barbecue ke캜upem, na코칤 nakl치danou zeleninou a raj캜치tkem, sezamov치 sem칤nka, + na코e dom치c칤 hranolky A : 1,3,6,7,10,11",
      "price": 157
    },
    {
      "name": "칔TER칗",
      "description": "칔TER칗-  POL칄VKA :::: Kuku콏i캜n칳 kr칠m s chilli vlasy a 캜erstv칳m koriandrem A: 1,7",
      "price": 47
    },
    {
      "name": "칔TER칗 - HLAVN칈 CHOD",
      "description": "칔TER칗 - HLAVN칈 CHOD ::: Penne se smetanovou om치캜kou z brokolice, blan코칤rovan치 brokolice a karotky, bylinky a sal치tek A : 7",
      "price": 127
    },
    {
      "name": "칔TER칗",
      "description": "칔TER칗 - HLAVN칈 CHOD :::  Burger s trhan칳m vep콏ov칳m bokem, 캜erstv칳m koriandrem, sriracha majon칠zou a dom치c칤m barbecue ke캜upem, na코칤 nakl치danou zeleninou a raj캜치tkem, sezamov치 sem칤nka, + na코e dom치c칤 hranolky A : 1,3,6,7,10,11",
      "price": 157
    },
    {
      "name": "ST콎EDA",
      "description": "ST콎EDA -  ZM캨NA -  POL칄VKA :::: Kuku콏i캜n칳 kr칠m s chilli vlasy a 캜erstv칳m koriandrem A: 1,7",
      "price": 47
    },
    {
      "name": "HLAVN칈 CHOD",
      "description": "ST콎EDA - HLAVN칈 CHOD ::: Dlouze pe캜en치 vep콏ov치 쬰bra s bramborovo k콏enov칳m pur칠 a mal칳m sal치tem",
      "price": 147
    },
    {
      "name": "HLAVN칈 CHOD",
      "description": "ST콎EDA - HLAVN칈 CHOD :::  Burger s trhan칳m vep콏ov칳m bokem, 캜erstv칳m koriandrem, sriracha majon칠zou a dom치c칤m barbecue ke캜upem, na코칤 nakl치danou zeleninou a raj캜치tkem, sezamov치 sem칤nka, + na코e dom치c칤 hranolky A : 1,3,6,7,10,11",
      "price": 147
    },
    {
      "name": "캛TVRTEK",
      "description": "캛TVRTEK - POL칄VKA :::::: Mrkvov칳 kr칠m s kokosov칳m ml칠kem a blan코칤rovanou karotkou (vegan) A : -",
      "price": 47
    },
    {
      "name": "캛TVRTEK - Hlavn칤 chod",
      "description": "캛TVRTEK - HLAVN칈 CHOD :::: Risotto z 캜erven칠 콏epy s hoblinkami s칳ru Gran Moravia, s 캜erstv칳mi bylinkami a na코칤m 코alv캩jov칳m olej칤캜kem ",
      "price": 127
    },
    {
      "name": "P츼TEK",
      "description": "P츼TEK - HLAVN칈 CHOD ::::: Hov캩z칤 burger z vyzr치l칠ho krku, s na코imi nakl치dan칳mi okurkami,  캜erstv칳m libe캜kem, dom치c칤m barbecue ke캜upem, ho콏캜i캜n칳m dipem, raj캜etem a listy sal치tu, na코e dom치c칤 hranolky  A:  1,3,6,7,10",
      "price": 157
    },
    {
      "name": "P츼TEK",
      "description": "P츼TEK - SLADK칄 ::: L칤vance s om치캜kou z jahod, citronov칠 mascarpone, hoblinky b칤l칠 a ho콏k칠 캜okol치dy, 캜erstv치 m치ta, p콏elit칠 vi코켿ov칳m sirupem A: 1,3,7",
      "price": 127
    }
  ]
}